{"#define RAPIDLZ_H": "0", "#define RAPIDLZ_STREAM_HASH_SIZE (1 << 12)": "1", "#define RAPIDLZ_INNER_H": "2", "#define X86_SSE2": "3", "#define ARM_NEON": "4", "#define RAPIDLZ_MAX_BYTE_VALUE 255": "5", "#define RAPIDLZ_MAX_4BIT_VALUE 15": "6", "#define RAPIDLZ_MIN_MATCH 4": "7", "#define RAPIDLZ_HASH_TYPE_4 4": "8", "#define RAPIDLZ_HASH_TYPE_5 5": "9", "#define RAPIDLZ_STEP_FORWARD_BASE 6": "10", "#define RAPIDLZ_MAX_OFFSET 65535": "11", "#define RAPIDLZ_INPUT_INVALID (size_t)(-100)": "12", "#define RAPIDLZ_MALLOC_FAILED (size_t)(-99)": "13", "#define RAPIDLZ_DST_SIZE_SMALL (size_t)(-98)": "14", "#define RAPIDLZ_SECUREC_ERROR (size_t)(-97)": "15", "#define RAPIDLZ_FORMAT_INVALID (size_t)(-96)": "16", "#define RAPIDLZ_ALWAYS_INLINE inline __attribute__((always_inline))": "17", "#define RAPIDLZ_ALWAYS_INLINE inline": "18", "#define RAPIDLZ_FOUR_BYTE 4": "19", "#define RAPIDLZ_EIGHT_BYTE 8": "20", "#define RAPIDLZ_SIXTEEN_BYTE 16": "21", "#define RAPIDLZ_COPY_PROTECT_SIZE 16": "22", "#define RAPIDLZ_FALLTHROUGH __attribute__((fallthrough))": "23", "#define RAPIDLZ_LOG_H": "24", "#define RAPIDLZFILENAME \"\"": "25", "#define RAPIDLZFILENAME (strrchr(__FILE__, '/') ? strrchr(__FILE__, '/') + 1 : __FILE__)": "26", "#define RAPIDLZ_MAX_DICT_SIZE (64 * 1024)": "27", "#define RAPIDLZ_LAST_LITERALS 5": "28", "#define RAPIDLZ_DEC_NOT_OK 0": "29", "#define RAPIDLZ_ERROR_PARAM_UNSUPPORTED (-1)": "30", "#define RAPIDLZ_ERROR_OUTPUT (int)(-((void *)curSrc - (void *)src) - 1)": "31", "#define RAPIDLZ_DICT_HASH_MOVE_BYTES 3": "32", "#define RAPIDLZ_STREAM_HASH_BYTES 4": "33", "#define RAPIDLZ_STREAM_ACCELERAT_MIN 1": "34", "#define RAPIDLZ_STREAM_ACCELERAT_MAX 10": "35", "#define RAPIDLZ_PTR_DIFF_MAX_32 0x80000000": "36", "#define RAPIDLZ_MAX_INPUT_SIZE 0x7E000000": "37", "#define RAPIDLZ_LAST_LITERAL_LENGTH 13": "38", "#define RAPIDLZ_ENC_NOT_OK 0": "39", "#define RAPIDLZ_FAST_DIST_MIN 64": "40", "#define RAPIDLZ_MIN_COMPRESSED_SIZE 12": "41", "#define RAPIDLZ_CURRENT_OFFSET (64 * 1024)": "42", "#define RAPIDLZ_GOLDEN_SECTION_PRIME 2654435761U": "43", "#define RAPIDLZ_STREAM_HASH_BITS 20": "44", "#define LOG_BUF_SIZE 1024": "45", "#define RAPIDLZ_MAX_4BIT_MATCH 19": "46", "#define RAPIDLZ_MAX_INPUT_SIZE 0x7E000000U": "47", "#define RAPIDLZ_ACCELERATION_MAX 10": "48", "#define RAPIDLZ_SRC_SIZE_THRESHOLD 65536": "49", "#define RAPIDLZ_LAST_LITERALS 6": "50", "#define RAPIDLZ_MIN_COMPRESS_SIZE 16": "51", "#define RAPIDLZ_MIN_HASH_BIT 6": "52", "#define RAPIDLZ_MAX_HASH_BIT 12": "53"}